{
    "2d.2": {
        "category": "music",
        "sounds": [
            {
                "name": "sounds/kami/2/d/2",
                "load_on_low_memory": true
            }
        ]
    },
    "2d.3": {
        "category": "music",
        "sounds": [
            {
                "name": "sounds/kami/2/d/3",
                "load_on_low_memory": true
            }
        ]
    },
    "2d.4": {
        "category": "music",
        "sounds": [
            {
                "name": "sounds/kami/2/d/4",
                "load_on_low_memory": true
            }
        ]
    },
    "2d.5": {
        "category": "music",
        "sounds": [
            {
                "name": "sounds/kami/2/d/5",
                "load_on_low_memory": true
            }
        ]
    },
    "2d.6": {
        "category": "music",
        "sounds": [
            {
                "name": "sounds/kami/2/d/6",
                "load_on_low_memory": true
            }
        ]
    },
    "2d.7": {
        "category": "music",
        "sounds": [
            {
                "name": "sounds/kami/2/d/7",
                "load_on_low_memory": true
            }
        ]
    },
    "2d.8": {
        "category": "music",
        "sounds": [
            {
                "name": "sounds/kami/2/d/8",
                "load_on_low_memory": true
            }
        ]
    },
    "2d.9": {
        "category": "music",
        "sounds": [
            {
                "name": "sounds/kami/2/d/9",
                "load_on_low_memory": true
            }
        ]
    },
    "2d.12": {
        "category": "music",
        "sounds": [
            {
                "name": "sounds/kami/2/d/12",
                "load_on_low_memory": true
            }
        ]
    },
    "2d.13": {
        "category": "music",
        "sounds": [
            {
                "name": "sounds/kami/2/d/13",
                "load_on_low_memory": true
            }
        ]
    },
    "2d.14": {
        "category": "music",
        "sounds": [
            {
                "name": "sounds/kami/2/d/14",
                "load_on_low_memory": true
            }
        ]
    },
    "2d.15": {
        "category": "music",
        "sounds": [
            {
                "name": "sounds/kami/2/d/15",
                "load_on_low_memory": true
            }
        ]
    },
    "2d.16": {
        "category": "music",
        "sounds": [
            {
                "name": "sounds/kami/2/d/16",
                "load_on_low_memory": true
            }
        ]
    },
    "2d.17": {
        "category": "music",
        "sounds": [
            {
                "name": "sounds/kami/2/d/17",
                "load_on_low_memory": true
            }
        ]
    },
    "2d.18": {
        "category": "music",
        "sounds": [
            {
                "name": "sounds/kami/2/d/18",
                "load_on_low_memory": true
            }
        ]
    },
    "2d.19": {
        "category": "music",
        "sounds": [
            {
                "name": "sounds/kami/2/d/19",
                "load_on_low_memory": true
            }
        ]
    },
    "2d.20": {
        "category": "music",
        "sounds": [
            {
                "name": "sounds/kami/2/d/20",
                "load_on_low_memory": true
            }
        ]
    },
    "2d.21": {
        "category": "music",
        "sounds": [
            {
                "name": "sounds/kami/2/d/21",
                "load_on_low_memory": true
            }
        ]
    },
    "2d.22": {
        "category": "music",
        "sounds": [
            {
                "name": "sounds/kami/2/d/22",
                "load_on_low_memory": true
            }
        ]
    },
    "2d.23": {
        "category": "music",
        "sounds": [
            {
                "name": "sounds/kami/2/d/23",
                "load_on_low_memory": true
            }
        ]
    },
    "2d.24": {
        "category": "music",
        "sounds": [
            {
                "name": "sounds/kami/2/d/24",
                "load_on_low_memory": true
            }
        ]
    },
    "2d.25": {
        "category": "music",
        "sounds": [
            {
                "name": "sounds/kami/2/d/25",
                "load_on_low_memory": true
            }
        ]
    },
    "2d.26": {
        "category": "music",
        "sounds": [
            {
                "name": "sounds/kami/2/d/26",
                "load_on_low_memory": true
            }
        ]
    },
    "2d.27": {
        "category": "music",
        "sounds": [
            {
                "name": "sounds/kami/2/d/27",
                "load_on_low_memory": true
            }
        ]
    },
    "2d.28": {
        "category": "music",
        "sounds": [
            {
                "name": "sounds/kami/2/d/28",
                "load_on_low_memory": true
            }
        ]
    },
    "2d.29": {
        "category": "music",
        "sounds": [
            {
                "name": "sounds/kami/2/d/29",
                "load_on_low_memory": true
            }
        ]
    },
    "2d.30": {
        "category": "music",
        "sounds": [
            {
                "name": "sounds/kami/2/d/30",
                "load_on_low_memory": true
            }
        ]
    },
    "2d.31": {
        "category": "music",
        "sounds": [
            {
                "name": "sounds/kami/2/d/31",
                "load_on_low_memory": true
            }
        ]
    },
    "2d.32": {
        "category": "music",
        "sounds": [
            {
                "name": "sounds/kami/2/d/32",
                "load_on_low_memory": true
            }
        ]
    },
    "2d.33": {
        "category": "music",
        "sounds": [
            {
                "name": "sounds/kami/2/d/33",
                "load_on_low_memory": true
            }
        ]
    },
    "2d.34": {
        "category": "music",
        "sounds": [
            {
                "name": "sounds/kami/2/d/34",
                "load_on_low_memory": true
            }
        ]
    },
    "2d.35": {
        "category": "music",
        "sounds": [
            {
                "name": "sounds/kami/2/d/35",
                "load_on_low_memory": true
            }
        ]
    },
    "2d.36": {
        "category": "music",
        "sounds": [
            {
                "name": "sounds/kami/2/d/36",
                "load_on_low_memory": true
            }
        ]
    },
    "2d.37": {
        "category": "music",
        "sounds": [
            {
                "name": "sounds/kami/2/d/37",
                "load_on_low_memory": true
            }
        ]
    },
    "2d.38": {
        "category": "music",
        "sounds": [
            {
                "name": "sounds/kami/2/d/38",
                "load_on_low_memory": true
            }
        ]
    },
    "2d.39": {
        "category": "music",
        "sounds": [
            {
                "name": "sounds/kami/2/d/39",
                "load_on_low_memory": true
            }
        ]
    },
    "2d.40": {
        "category": "music",
        "sounds": [
            {
                "name": "sounds/kami/2/d/40",
                "load_on_low_memory": true
            }
        ]
    },
    "2d.41": {
        "category": "music",
        "sounds": [
            {
                "name": "sounds/kami/2/d/41",
                "load_on_low_memory": true
            }
        ]
    },
    "2d.42": {
        "category": "music",
        "sounds": [
            {
                "name": "sounds/kami/2/d/42",
                "load_on_low_memory": true
            }
        ]
    },
    "2d.43": {
        "category": "music",
        "sounds": [
            {
                "name": "sounds/kami/2/d/43",
                "load_on_low_memory": true
            }
        ]
    },
    "2d.44": {
        "category": "music",
        "sounds": [
            {
                "name": "sounds/kami/2/d/44",
                "load_on_low_memory": true
            }
        ]
    },
    "2d.45": {
        "category": "music",
        "sounds": [
            {
                "name": "sounds/kami/2/d/45",
                "load_on_low_memory": true
            }
        ]
    },
    "2d.46": {
        "category": "music",
        "sounds": [
            {
                "name": "sounds/kami/2/d/46",
                "load_on_low_memory": true
            }
        ]
    },
    "2d.47": {
        "category": "music",
        "sounds": [
            {
                "name": "sounds/kami/2/d/47",
                "load_on_low_memory": true
            }
        ]
    },
    "2d.48": {
        "category": "music",
        "sounds": [
            {
                "name": "sounds/kami/2/d/48",
                "load_on_low_memory": true
            }
        ]
    },
    "2d.49": {
        "category": "music",
        "sounds": [
            {
                "name": "sounds/kami/2/d/49",
                "load_on_low_memory": true
            }
        ]
    },
    "2d.50": {
        "category": "music",
        "sounds": [
            {
                "name": "sounds/kami/2/d/50",
                "load_on_low_memory": true
            }
        ]
    },
    "2d.51": {
        "category": "music",
        "sounds": [
            {
                "name": "sounds/kami/2/d/51",
                "load_on_low_memory": true
            }
        ]
    },
    "2d.52": {
        "category": "music",
        "sounds": [
            {
                "name": "sounds/kami/2/d/52",
                "load_on_low_memory": true
            }
        ]
    },
    "2d.53": {
        "category": "music",
        "sounds": [
            {
                "name": "sounds/kami/2/d/53",
                "load_on_low_memory": true
            }
        ]
    },
    "2d.54": {
        "category": "music",
        "sounds": [
            {
                "name": "sounds/kami/2/d/54",
                "load_on_low_memory": true
            }
        ]
    },
    "2d.55": {
        "category": "music",
        "sounds": [
            {
                "name": "sounds/kami/2/d/55",
                "load_on_low_memory": true
            }
        ]
    },
    "2d.56": {
        "category": "music",
        "sounds": [
            {
                "name": "sounds/kami/2/d/56",
                "load_on_low_memory": true
            }
        ]
    },
    "2d.57": {
        "category": "music",
        "sounds": [
            {
                "name": "sounds/kami/2/d/57",
                "load_on_low_memory": true
            }
        ]
    },
    "2d.58": {
        "category": "music",
        "sounds": [
            {
                "name": "sounds/kami/2/d/58",
                "load_on_low_memory": true
            }
        ]
    },
    "2d.59": {
        "category": "music",
        "sounds": [
            {
                "name": "sounds/kami/2/d/59",
                "load_on_low_memory": true
            }
        ]
    },
    "2d.60": {
        "category": "music",
        "sounds": [
            {
                "name": "sounds/kami/2/d/60",
                "load_on_low_memory": true
            }
        ]
    },
    "2d.61": {
        "category": "music",
        "sounds": [
            {
                "name": "sounds/kami/2/d/61",
                "load_on_low_memory": true
            }
        ]
    },
    "2d.62": {
        "category": "music",
        "sounds": [
            {
                "name": "sounds/kami/2/d/62",
                "load_on_low_memory": true
            }
        ]
    },
    "2d.63": {
        "category": "music",
        "sounds": [
            {
                "name": "sounds/kami/2/d/63",
                "load_on_low_memory": true
            }
        ]
    },
    "2d.64": {
        "category": "music",
        "sounds": [
            {
                "name": "sounds/kami/2/d/64",
                "load_on_low_memory": true
            }
        ]
    },
    "2d.65": {
        "category": "music",
        "sounds": [
            {
                "name": "sounds/kami/2/d/65",
                "load_on_low_memory": true
            }
        ]
    },
    "2d.66": {
        "category": "music",
        "sounds": [
            {
                "name": "sounds/kami/2/d/66",
                "load_on_low_memory": true
            }
        ]
    },
    "2d.67": {
        "category": "music",
        "sounds": [
            {
                "name": "sounds/kami/2/d/67",
                "load_on_low_memory": true
            }
        ]
    },
    "2d.68": {
        "category": "music",
        "sounds": [
            {
                "name": "sounds/kami/2/d/68",
                "load_on_low_memory": true
            }
        ]
    },
    "2d.69": {
        "category": "music",
        "sounds": [
            {
                "name": "sounds/kami/2/d/69",
                "load_on_low_memory": true
            }
        ]
    },
    "2d.70": {
        "category": "music",
        "sounds": [
            {
                "name": "sounds/kami/2/d/70",
                "load_on_low_memory": true
            }
        ]
    },
    "2d.71": {
        "category": "music",
        "sounds": [
            {
                "name": "sounds/kami/2/d/71",
                "load_on_low_memory": true
            }
        ]
    },
    "2d.72": {
        "category": "music",
        "sounds": [
            {
                "name": "sounds/kami/2/d/72",
                "load_on_low_memory": true
            }
        ]
    },
    "2d.73": {
        "category": "music",
        "sounds": [
            {
                "name": "sounds/kami/2/d/73",
                "load_on_low_memory": true
            }
        ]
    },
    "2d.74": {
        "category": "music",
        "sounds": [
            {
                "name": "sounds/kami/2/d/74",
                "load_on_low_memory": true
            }
        ]
    },
    "2d.75": {
        "category": "music",
        "sounds": [
            {
                "name": "sounds/kami/2/d/75",
                "load_on_low_memory": true
            }
        ]
    },
    "2d.76": {
        "category": "music",
        "sounds": [
            {
                "name": "sounds/kami/2/d/76",
                "load_on_low_memory": true
            }
        ]
    },
    "2d.77": {
        "category": "music",
        "sounds": [
            {
                "name": "sounds/kami/2/d/77",
                "load_on_low_memory": true
            }
        ]
    },
    "2d.78": {
        "category": "music",
        "sounds": [
            {
                "name": "sounds/kami/2/d/78",
                "load_on_low_memory": true
            }
        ]
    },
    "2d.79": {
        "category": "music",
        "sounds": [
            {
                "name": "sounds/kami/2/d/79",
                "load_on_low_memory": true
            }
        ]
    },
    "2d.80": {
        "category": "music",
        "sounds": [
            {
                "name": "sounds/kami/2/d/80",
                "load_on_low_memory": true
            }
        ]
    },
    "2d.81": {
        "category": "music",
        "sounds": [
            {
                "name": "sounds/kami/2/d/81",
                "load_on_low_memory": true
            }
        ]
    },
    "2d.82": {
        "category": "music",
        "sounds": [
            {
                "name": "sounds/kami/2/d/82",
                "load_on_low_memory": true
            }
        ]
    },
    "2d.83": {
        "category": "music",
        "sounds": [
            {
                "name": "sounds/kami/2/d/83",
                "load_on_low_memory": true
            }
        ]
    },
    "2d.84": {
        "category": "music",
        "sounds": [
            {
                "name": "sounds/kami/2/d/84",
                "load_on_low_memory": true
            }
        ]
    },
    "2d.85": {
        "category": "music",
        "sounds": [
            {
                "name": "sounds/kami/2/d/85",
                "load_on_low_memory": true
            }
        ]
    },
    "2d.86": {
        "category": "music",
        "sounds": [
            {
                "name": "sounds/kami/2/d/86",
                "load_on_low_memory": true
            }
        ]
    },
    "2d.87": {
        "category": "music",
        "sounds": [
            {
                "name": "sounds/kami/2/d/87",
                "load_on_low_memory": true
            }
        ]
    },
    "2d.88": {
        "category": "music",
        "sounds": [
            {
                "name": "sounds/kami/2/d/88",
                "load_on_low_memory": true
            }
        ]
    },
    "2d.89": {
        "category": "music",
        "sounds": [
            {
                "name": "sounds/kami/2/d/89",
                "load_on_low_memory": true
            }
        ]
    },
    "2d.90": {
        "category": "music",
        "sounds": [
            {
                "name": "sounds/kami/2/d/90",
                "load_on_low_memory": true
            }
        ]
    },
    "2d.91": {
        "category": "music",
        "sounds": [
            {
                "name": "sounds/kami/2/d/91",
                "load_on_low_memory": true
            }
        ]
    },
    "2d.92": {
        "category": "music",
        "sounds": [
            {
                "name": "sounds/kami/2/d/92",
                "load_on_low_memory": true
            }
        ]
    },
    "2d.93": {
        "category": "music",
        "sounds": [
            {
                "name": "sounds/kami/2/d/93",
                "load_on_low_memory": true
            }
        ]
    },
    "2d.94": {
        "category": "music",
        "sounds": [
            {
                "name": "sounds/kami/2/d/94",
                "load_on_low_memory": true
            }
        ]
    },
    "2d.95": {
        "category": "music",
        "sounds": [
            {
                "name": "sounds/kami/2/d/95",
                "load_on_low_memory": true
            }
        ]
    },
    "2d.96": {
        "category": "music",
        "sounds": [
            {
                "name": "sounds/kami/2/d/96",
                "load_on_low_memory": true
            }
        ]
    },
    "2d.97": {
        "category": "music",
        "sounds": [
            {
                "name": "sounds/kami/2/d/97",
                "load_on_low_memory": true
            }
        ]
    },
    "2d.98": {
        "category": "music",
        "sounds": [
            {
                "name": "sounds/kami/2/d/98",
                "load_on_low_memory": true
            }
        ]
    },
    "2d.99": {
        "category": "music",
        "sounds": [
            {
                "name": "sounds/kami/2/d/99",
                "load_on_low_memory": true
            }
        ]
    },
    "2d.111": {
        "category": "music",
        "sounds": [
            {
                "name": "sounds/kami/2/d/111",
                "load_on_low_memory": true
            }
        ]
    },
    "2d.112": {
        "category": "music",
        "sounds": [
            {
                "name": "sounds/kami/2/d/112",
                "load_on_low_memory": true
            }
        ]
    },
    "2d.113": {
        "category": "music",
        "sounds": [
            {
                "name": "sounds/kami/2/d/113",
                "load_on_low_memory": true
            }
        ]
    },
    "2d.114": {
        "category": "music",
        "sounds": [
            {
                "name": "sounds/kami/2/d/114",
                "load_on_low_memory": true
            }
        ]
    },
    "2d.115": {
        "category": "music",
        "sounds": [
            {
                "name": "sounds/kami/2/d/115",
                "load_on_low_memory": true
            }
        ]
    },
    "2d.116": {
        "category": "music",
        "sounds": [
            {
                "name": "sounds/kami/2/d/116",
                "load_on_low_memory": true
            }
        ]
    },
    "2d.117": {
        "category": "music",
        "sounds": [
            {
                "name": "sounds/kami/2/d/117",
                "load_on_low_memory": true
            }
        ]
    },
    "2d.118": {
        "category": "music",
        "sounds": [
            {
                "name": "sounds/kami/2/d/118",
                "load_on_low_memory": true
            }
        ]
    },
    "2d.119": {
        "category": "music",
        "sounds": [
            {
                "name": "sounds/kami/2/d/119",
                "load_on_low_memory": true
            }
        ]
    },
    "2d.120": {
        "category": "music",
        "sounds": [
            {
                "name": "sounds/kami/2/d/120",
                "load_on_low_memory": true
            }
        ]
    },
    "2d.121": {
        "category": "music",
        "sounds": [
            {
                "name": "sounds/kami/2/d/121",
                "load_on_low_memory": true
            }
        ]
    },
    "2d.122": {
        "category": "music",
        "sounds": [
            {
                "name": "sounds/kami/2/d/122",
                "load_on_low_memory": true
            }
        ]
    },
    "2d.123": {
        "category": "music",
        "sounds": [
            {
                "name": "sounds/kami/2/d/123",
                "load_on_low_memory": true
            }
        ]
    },
    "2d.124": {
        "category": "music",
        "sounds": [
            {
                "name": "sounds/kami/2/d/124",
                "load_on_low_memory": true
            }
        ]
    },
    "2d.125": {
        "category": "music",
        "sounds": [
            {
                "name": "sounds/kami/2/d/125",
                "load_on_low_memory": true
            }
        ]
    },
    "2d.126": {
        "category": "music",
        "sounds": [
            {
                "name": "sounds/kami/2/d/126",
                "load_on_low_memory": true
            }
        ]
    },
    "2d.127": {
        "category": "music",
        "sounds": [
            {
                "name": "sounds/kami/2/d/127",
                "load_on_low_memory": true
            }
        ]
    }
}